atpt/__init__.py
atpt/fdm.py
atpt-0.0.0.dist-info/AUTHORS.rst
atpt-0.0.0.dist-info/LICENSE
atpt-0.0.0.dist-info/METADATA
atpt-0.0.0.dist-info/WHEEL
atpt-0.0.0.dist-info/top_level.txt
atpt-0.0.0.dist-info/RECORD
