Metadata-Version: 2.1
Name: atpt
Version: 0.0.0
Summary: Implementation of augmented transition path theory.
Home-page: https://github.com/dinner-group/atpt
Author: Chatipat Lorpaiboon
Author-email: chatipat@uchicago.edu
License: MIT
Project-URL: Documentation, https://atpt.readthedocs.io/
Project-URL: Changelog, https://atpt.readthedocs.io/en/latest/changelog.html
Project-URL: Issue Tracker, https://github.com/dinner-group/atpt/issues
Classifier: Development Status :: 3 - Alpha
Classifier: Intended Audience :: Science/Research
Classifier: License :: OSI Approved :: MIT License
Classifier: Operating System :: Unix
Classifier: Operating System :: POSIX
Classifier: Operating System :: Microsoft :: Windows
Classifier: Programming Language :: Python
Classifier: Programming Language :: Python :: 3
Classifier: Programming Language :: Python :: 3 :: Only
Classifier: Programming Language :: Python :: 3.7
Classifier: Programming Language :: Python :: 3.8
Classifier: Programming Language :: Python :: 3.9
Classifier: Programming Language :: Python :: 3.10
Classifier: Programming Language :: Python :: Implementation :: CPython
Classifier: Topic :: Scientific/Engineering
Requires-Python: >=3.7
License-File: LICENSE
License-File: AUTHORS.rst
Requires-Dist: numpy
Requires-Dist: scipy
